imailing/Mailing.py
imailing/Sendgrid.py
imailing/SendinBlue.py
imailing/__init__.py
imailing/cli.py
imailing-1.0.0.dist-info/DESCRIPTION.rst
imailing-1.0.0.dist-info/METADATA
imailing-1.0.0.dist-info/RECORD
imailing-1.0.0.dist-info/WHEEL
imailing-1.0.0.dist-info/entry_points.txt
imailing-1.0.0.dist-info/metadata.json
imailing-1.0.0.dist-info/top_level.txt
