Metadata-Version: 2.0
Name: imailing
Version: 1.0.0
Summary: Interface to send transactionnal email with differents services 
Home-page: https://github.com/RignonNoel/imailing
Author: Noël Rignon
Author-email: rignon.noel@gmail.com
License: MIT license
Keywords: imailing
Platform: UNKNOWN
Classifier: Development Status :: 2 - Pre-Alpha
Classifier: Intended Audience :: Developers
Classifier: License :: OSI Approved :: MIT License
Classifier: Natural Language :: English
Classifier: Programming Language :: Python :: 2
Classifier: Programming Language :: Python :: 2.7
Classifier: Programming Language :: Python :: 3
Classifier: Programming Language :: Python :: 3.4
Classifier: Programming Language :: Python :: 3.5
Classifier: Programming Language :: Python :: 3.6
Requires-Dist: Click (>=6.0)
Requires-Dist: Sendinblue (>=2.0.5.1)
Requires-Dist: sendgrid (>=5.3.0)
